pipemake/__init__.py
pipemake/fileIO.py
pipemake/logger.py
pipemake/parser.py
pipemake/pathIO.py
pipemake/pipelineIO.py
pipemake/pipemake.py
pipemake/processIO.py
pipemake/singularityIO.py
pipemake/snakemakeIO.py
pipemake/wildcardIO.py
pipemake-1.3.2.dist-info/licenses/LICENSE
pipemake-1.3.2.dist-info/METADATA
pipemake-1.3.2.dist-info/WHEEL
pipemake-1.3.2.dist-info/entry_points.txt
pipemake-1.3.2.dist-info/top_level.txt
pipemake-1.3.2.dist-info/RECORD
