Metadata-Version: 2.4
Name: pipemake
Version: 1.3.2
Summary: Pipemake: A pipeline creation tool using Snakemake
Home-page: https://github.com/kocherlab/pipemake
License: MIT
Project-URL: Documentation, https://pipemake.readthedocs.io/en/latest/
Project-URL: Code, https://github.com/kocherlab/pipemake
Project-URL: Issue tracker, https://github.com/kocherlab/pipemake/issues
Requires-Python: >=3.7
License-File: LICENSE
Dynamic: description
Dynamic: description-content-type
Dynamic: home-page
Dynamic: license
Dynamic: license-file
Dynamic: project-url
Dynamic: requires-python
Dynamic: summary
